xmemo/__init__.py
xmemo/analyzer.py
xmemo/langgraph_tracker.py
xmemo/models.py
xmemo/reflection.py
xmemo-0.2.0.dist-info/METADATA
xmemo-0.2.0.dist-info/WHEEL
xmemo-0.2.0.dist-info/top_level.txt
xmemo-0.2.0.dist-info/RECORD
