Metadata-Version: 2.1
Name: xmemo
Version: 0.2.0
Summary: A Python package for recording agent memory and reflection from conversations
Home-page: https://github.com/sairin1202/Xmemo
Author: sairin1202
Author-email: sairin1202@github.com
Classifier: Development Status :: 3 - Alpha
Classifier: Intended Audience :: Developers
Classifier: Operating System :: OS Independent
Classifier: Programming Language :: Python :: 3
Classifier: Programming Language :: Python :: 3.10
Classifier: Programming Language :: Python :: 3.11
Classifier: Programming Language :: Python :: 3.12
Requires-Python: >=3.10
Requires-Dist: pydantic>=2.0.0
Requires-Dist: typing-extensions>=4.0.0
Provides-Extra: all
Requires-Dist: openai>=1.0.0; extra == "all"
Requires-Dist: anthropic>=0.21.0; extra == "all"
Provides-Extra: claude
Requires-Dist: anthropic>=0.21.0; extra == "claude"
Provides-Extra: dev
Requires-Dist: pytest>=7.0.0; extra == "dev"
Requires-Dist: pytest-cov>=4.0.0; extra == "dev"
Requires-Dist: black>=23.0.0; extra == "dev"
Requires-Dist: isort>=5.12.0; extra == "dev"
Requires-Dist: flake8>=6.0.0; extra == "dev"
Requires-Dist: mypy>=1.0.0; extra == "dev"
Provides-Extra: integrations
Requires-Dist: openai>=1.0.0; extra == "integrations"
Requires-Dist: anthropic>=0.21.0; extra == "integrations"
Provides-Extra: openai
Requires-Dist: openai>=1.0.0; extra == "openai"
